setup.py
celerybeat_redis.egg-info/PKG-INFO
celerybeat_redis.egg-info/SOURCES.txt
celerybeat_redis.egg-info/dependency_links.txt
celerybeat_redis.egg-info/requires.txt
celerybeat_redis.egg-info/top_level.txt
celerybeatredis/__init__.py
celerybeatredis/decoder.py
celerybeatredis/exceptions.py
celerybeatredis/globals.py
celerybeatredis/schedulers.py
celerybeatredis/task.py