Metadata-Version: 1.0
Name: celerybeat-redis
Version: 0.1.5
Summary: A Celery Beat Scheduler that uses Redis to store both schedule definitions and status information
Home-page: UNKNOWN
Author: Kong Luoxing
Author-email: kong.luoxing@gmail.com
License: Apache License, Version 2.0
Keywords: python celery beat redis
Platform: UNKNOWN
